__init__.py
center_widget.py
custom_logger.py
info_bar.py
left_sidebar.py
main.py
right_sidebar.py
statusbar.py
testpython.py
toolbar.py
version.py
Updater/__init__.py
Updater/autoUpdate.py
Updater/downloadFile.py
Updater/handleZip.py
Updater/ui_winUpdate.py
Updater/updateVersion.py
Updater/updateWindow.py
Updater/update_image_rc.py
suan_pyqt_vtk_mat-0.1.24.dist-info/LICENSE
suan_pyqt_vtk_mat-0.1.24.dist-info/METADATA
suan_pyqt_vtk_mat-0.1.24.dist-info/WHEEL
suan_pyqt_vtk_mat-0.1.24.dist-info/top_level.txt
suan_pyqt_vtk_mat-0.1.24.dist-info/RECORD
